setup.py
python/xslcover/__init__.py
python/xslcover/config.py
python/xslcover/coverapi.py
python/xslcover/coverfile.py
python/xslcover/htmlreport.py
python/xslcover/runcover.py
python/xslcover/runner.py
python/xslcover/saxon_xslt2.py
python/xslcover/saxontrace.py
python/xslcover/xmlcover.py
python/xslcover/xslcoverage.py
python/xslcover/htdocs/__init__.py
python/xslcover/runners/__init__.py
python/xslcover/runners/dblatex.py
python/xslcover/runners/saxon.py
python/xslcover/runners/saxon9he.py
scripts/saxon-xslt2
scripts/xslcoverage
xslcoverage.egg-info/PKG-INFO
xslcoverage.egg-info/SOURCES.txt
xslcoverage.egg-info/dependency_links.txt
xslcoverage.egg-info/top_level.txt