Metadata-Version: 1.1
Name: xslcoverage
Version: 0.1.4
Summary: Scripts to compute the XSL Coverage done by an XSLT
Home-page: https://marsgui.github.io/xslcoverage
Author: Benoit Guillon
Author-email: marsgui@users.sourceforge.net
License: GPL Version 2 or later
Platform: UNKNOWN
Classifier: Operating System :: OS Independent
Classifier: Topic :: Text Processing :: Markup :: XML
Classifier: License :: OSI Approved :: GNU General Public License (GPL)
